{
    "keys": [
        "App Settings",
        "Assigned",
        "Dashboard",
        "Email",
        "Help & Support",
        "Here’s your overview for today",
        "Images",
        "InspectioniQ",
        "Inspections",
        "Inward",
        "Inward Entry",
        "Logout",
        "Main Categories",
        "Notifications",
        "Pending",
        "Performance Overview",
        "Privacy & Security",
        "Profile",
        "Recent Activity",
        "Role",
        "Select a category to begin your workflow",
        "Settings",
        "Total Completed",
        "Vehicle Images uploads",
        "Vehicle Inspection",
        "Vehicle inspection process",
        "Vehicle reception and barcode printing",
        "Vehicles",
        "Vehicles washing process",
        "View All",
        "View Details",
        "Washing",
        "Welcome back"
    ],
    "locales": {
        "ar_AE": {
            "i18nStrings": {
                "App Settings": "إعدادات التطبيق",
                "Assigned": "مُكَلَّف",
                "Dashboard": "لوحة القيادة",
                "Email": "بريد إلكتروني",
                "Help & Support": "المساعدة والدعم",
                "Here’s your overview for today": "إليكم ملخص أحداث اليوم",
                "Images": "الصور",
                "InspectioniQ": "Qiتقتيش",
                "Inspections": "عمليات التفتيش",
                "Inward": "إلى الداخل",
                "Inward Entry": "الدخول إلى الداخل",
                "Logout": "تسجيل الخروج",
                "Main Categories": "الفئات الرئيسية",
                "Notifications": "إشعارات",
                "Pending": "قيد الانتظار",
                "Performance Overview": "نظرة عامة على الأداء",
                "Privacy & Security": "الخصوصية والأمن",
                "Profile": "حساب تعريفي",
                "Recent Activity": "النشاط الأخير",
                "Role": "دور",
                "Select a category to begin your workflow": "اختر فئة لبدء سير عملك",
                "Settings": "إعدادات",
                "Total Completed": "إجمالي مكتمل",
                "Vehicle Images uploads": "تحميل صور المركبات",
                "Vehicle Inspection": "فحص المركبات",
                "Vehicle inspection process": "عملية فحص المركبة",
                "Vehicle reception and barcode printing": "استقبال المركبات وطباعة الرموز الشريطية",
                "Vehicles": "المركبات",
                "Vehicles washing process": "عملية غسيل المركبات",
                "View All": "عرض الكل",
                "View Details": "عرض التفاصيل",
                "Washing": "غسل",
                "Welcome back": "مرحبًا بعودتك"
            },
            "isCustomLocale": false,
            "isSelected": true,
            "layoutConfig": {
                "mirrorContentAlignment": true,
                "mirrorFlexPositionProperties": true,
                "mirrorFlowHorizontalAlignment": true
            }
        },
        "en_IN": {
            "i18nStrings": {
                "App Settings": "App Settings",
                "Assigned": "Assigned",
                "Dashboard": "Dashboard",
                "Email": "Email",
                "Help & Support": "Help & Support",
                "Here’s your overview for today": "Here’s your overview for today",
                "Images": "Images",
                "InspectioniQ": "InspectioniQ",
                "Inspections": "Inspections",
                "Inward": "Inward",
                "Inward Entry": "Inward Entry",
                "Logout": "Logout",
                "Main Categories": "Main Categories",
                "Notifications": "Notifications",
                "Pending": "Pending",
                "Performance Overview": "Performance Overview",
                "Privacy & Security": "Privacy & Security",
                "Profile": "Profile",
                "Recent Activity": "Recent Activity",
                "Role": "Role",
                "Select a category to begin your workflow": "Select a category to begin your workflow",
                "Settings": "Settings",
                "Total Completed": "Total Completed",
                "Vehicle Images uploads": "Vehicle Images uploads",
                "Vehicle Inspection": "Vehicle Inspection",
                "Vehicle inspection process": "Vehicle inspection process",
                "Vehicle reception and barcode printing": "Vehicle reception and barcode printing",
                "Vehicles": "Vehicles",
                "Vehicles washing process": "Vehicles washing process",
                "View All": "View All",
                "View Details": "View Details",
                "Washing": "Washing",
                "Welcome back": "Welcome back"
            },
            "isCustomLocale": false,
            "isSelected": true,
            "layoutConfig": {
                "mirrorContentAlignment": false,
                "mirrorFlexPositionProperties": false,
                "mirrorFlowHorizontalAlignment": false
            }
        }
    }
}